odoo/addons/stock_available_to_promise_release_dynamic_routing/README.rst
odoo/addons/stock_available_to_promise_release_dynamic_routing/__init__.py
odoo/addons/stock_available_to_promise_release_dynamic_routing/__manifest__.py
odoo/addons/stock_available_to_promise_release_dynamic_routing/i18n/es_AR.po
odoo/addons/stock_available_to_promise_release_dynamic_routing/i18n/it.po
odoo/addons/stock_available_to_promise_release_dynamic_routing/i18n/pt_BR.po
odoo/addons/stock_available_to_promise_release_dynamic_routing/i18n/stock_available_to_promise_release_dynamic_routing.pot
odoo/addons/stock_available_to_promise_release_dynamic_routing/readme/CONTRIBUTORS.md
odoo/addons/stock_available_to_promise_release_dynamic_routing/readme/CREDITS.md
odoo/addons/stock_available_to_promise_release_dynamic_routing/readme/DESCRIPTION.md
odoo/addons/stock_available_to_promise_release_dynamic_routing/static/description/icon.png
odoo/addons/stock_available_to_promise_release_dynamic_routing/static/description/index.html
odoo/addons/stock_available_to_promise_release_dynamic_routing/tests/__init__.py
odoo/addons/stock_available_to_promise_release_dynamic_routing/tests/test_release_dynamic_routing.py
odoo_addon_stock_available_to_promise_release_dynamic_routing-18.0.1.0.1.dist-info/METADATA
odoo_addon_stock_available_to_promise_release_dynamic_routing-18.0.1.0.1.dist-info/WHEEL
odoo_addon_stock_available_to_promise_release_dynamic_routing-18.0.1.0.1.dist-info/top_level.txt
odoo_addon_stock_available_to_promise_release_dynamic_routing-18.0.1.0.1.dist-info/RECORD
