Metadata-Version: 2.1
Name: odoo-addon-stock_available_to_promise_release_dynamic_routing
Version: 18.0.1.0.1
Requires-Python: >=3.10
Requires-Dist: odoo-addon-stock_available_to_promise_release==18.0.*
Requires-Dist: odoo-addon-stock_dynamic_routing==18.0.*
Requires-Dist: odoo==18.0.*
Summary: Glue between moves release and dynamic routing
Home-page: https://github.com/OCA/stock-logistics-reservation
License: AGPL-3
Author: Camptocamp,BCIM,Odoo Community Association (OCA)
Author-email: support@odoo-community.org
Classifier: Programming Language :: Python
Classifier: Framework :: Odoo
Classifier: Framework :: Odoo :: 18.0
Classifier: License :: OSI Approved :: GNU Affero General Public License v3
Classifier: Development Status :: 3 - Alpha
